sortedcollections/__init__.py
sortedcollections/ordereddict.py
sortedcollections/recipes.py
sortedcollections-2.0.1.dist-info/LICENSE
sortedcollections-2.0.1.dist-info/METADATA
sortedcollections-2.0.1.dist-info/WHEEL
sortedcollections-2.0.1.dist-info/top_level.txt
sortedcollections-2.0.1.dist-info/RECORD
